{
  "generator-jhipster": {
    "jhipsterVersion": "3.5.1",
    "baseName": "prueba",
    "packageName": "com.belen.pruebajh",
    "packageFolder": "com/belen/pruebajh",
    "serverPort": "8080",
    "authenticationType": "session",
    "hibernateCache": "no",
    "clusteredHttpSession": "no",
    "websocket": "no",
    "databaseType": "sql",
    "devDatabaseType": "mariadb",
    "prodDatabaseType": "mariadb",
    "searchEngine": "no",
    "buildTool": "maven",
    "enableSocialSignIn": false,
    "rememberMeKey": "ad26337ef075c2f8d55e800db95d00866823a251",
    "useSass": false,
    "applicationType": "monolith",
    "testFrameworks": [
      "gatling"
    ],
    "jhiPrefix": "jhi",
    "enableTranslation": false
  }
}